api/README.md
api/__init__.py
api/client/__init__.py
api/client/batch_client/__init__.py
api/client/cfg/__init__.py
api/client/crop_model/__init__.py
api/client/gro_client/__init__.py
api/client/lib/__init__.py
groclient/__init__.py
groclient/__main__.py
groclient/batch_client_test.py
groclient/cfg.py
groclient/cli.py
groclient/client.py
groclient/client_test.py
groclient/constants.py
groclient/crop_model.py
groclient/lib.py
groclient/lib_test.py
groclient/mock_data.py
groclient/utils.py
groclient/utils_test.py
groclient_fork_tests-1.902.0.dist-info/entry_points.txt
groclient_fork_tests-1.902.0.dist-info/LICENSE
groclient_fork_tests-1.902.0.dist-info/WHEEL
groclient_fork_tests-1.902.0.dist-info/METADATA
groclient_fork_tests-1.902.0.dist-info/RECORD
