Metadata-Version: 2.1
Name: groclient-fork-tests
Version: 1.902.0
Summary: Python client library for accessing Gro Intelligence's agricultural data platform
Home-page: https://gro-intelligence.com/platform/api
License: MIT
Author: Gro Intelligence
Author-email: dev@gro-intelligence.com
Requires-Python: >=3.6.1,<4.0.0
Classifier: License :: OSI Approved :: MIT License
Classifier: Programming Language :: Python :: 3
Classifier: Programming Language :: Python :: 3.7
Classifier: Programming Language :: Python :: 3.8
Classifier: Programming Language :: Python :: 3.9
Classifier: Programming Language :: Python :: 3.10
Requires-Dist: numpy
Requires-Dist: pandas
Requires-Dist: requests
Requires-Dist: tornado
Requires-Dist: unicodecsv
Project-URL: Documentation, https://developers.gro-intelligence.com/
Project-URL: Repository, https://github.com/eric-gro/api-client-fork
